kewr/__init__.py
kewr/__main__.py
kewr/utils.py
kewr-0.3.1.dist-info/LICENSE
kewr-0.3.1.dist-info/WHEEL
kewr-0.3.1.dist-info/METADATA
kewr-0.3.1.dist-info/RECORD
