Metadata-Version: 2.1
Name: kewr
Version: 0.3.1
Summary: A simple python script manager
License: MIT
Author: Henry Watkins
Author-email: h.watkins@ucl.ac.uk
Requires-Python: >=3.8,<4.0
Classifier: License :: OSI Approved :: MIT License
Classifier: Programming Language :: Python :: 3
Classifier: Programming Language :: Python :: 3.8
Classifier: Programming Language :: Python :: 3.9
Classifier: Programming Language :: Python :: 3.10
Classifier: Programming Language :: Python :: 3.11
Requires-Dist: click (>=8.1.3,<9.0.0)
Requires-Dist: confection (>=0.0.4,<0.0.5)
